py_artisan/__init__.py
py_artisan/ai/__init__.py
py_artisan/ai/openai_utils.py
py_artisan/ai/text_utils.py
py_artisan/ai/langchain/__init__.py
py_artisan/ai/langchain/langchain_utils.py
py_artisan/ai/langchain/llm_facetory.py
py_artisan/ai/langchain/agents/__init__.py
py_artisan/ai/langchain/agents/base.py
py_artisan/utils/__init__.py
py_artisan/utils/config.py
py_artisan/utils/file_downloader.py
py_artisan/utils/time_utils.py
py_artisan-0.0.6.dist-info/LICENSE
py_artisan-0.0.6.dist-info/METADATA
py_artisan-0.0.6.dist-info/WHEEL
py_artisan-0.0.6.dist-info/top_level.txt
py_artisan-0.0.6.dist-info/RECORD
