Metadata-Version: 2.1
Name: py_artisan
Version: 0.0.6
Summary: 一个优雅好用的 Python 工具包
Home-page: https://github.com/wxytjustb/py-artisan
Author: rokywang
Author-email: rokywang <wxytjustb@gmail.com>
License: MIT License
Project-URL: Homepage, https://github.com/wxytjustb/py-artisan
Project-URL: Repository, https://github.com/wxytjustb/py-artisan.git
Classifier: Programming Language :: Python :: 3
Classifier: License :: OSI Approved :: MIT License
Classifier: Operating System :: OS Independent
Requires-Python: >=3.6
License-File: LICENSE
Provides-Extra: dev
